{"menu": {"0": {"bf": {"BREAKFAST 1": {"name": "Aloo Paratha", "eggy": "VEG"}, "BREAKFAST 2": {"name": "Kaju Pongal", "eggy": "VEG"}, "SAMBAR OR KETCHUP": {"name": "Mt", "eggy": "VEG"}, "CURD": {"name": "Curd", "eggy": "VEG"}, "CHUTNEY": {"name": "Green Mint Chutney", "eggy": "VEG"}, "EGG": {"name": "Mt", "eggy": "VEG"}, "JUICE/MILK SHAKE": {"name": "Mt", "eggy": "VEG"}}, "ln": {"INDIAN BREAD": {"name": "Bhature", "eggy": "VEG"}, "VEG GRAVY": {"name": "Pindi Chole", "eggy": "VEG"}, "VEG DRY/ STARTERS": {"name": "Hara Bhara Kebab", "eggy": "VEG"}, "FLAVORED RICE": {"name": "Veg Pulao", "eggy": "VEG"}, "PLAIN RICE": {"name": "Plain Rice", "eggy": "VEG"}, "DAL": {"name": "Dal Panchmel", "eggy": "VEG"}, "SAMBAR OR RASAM": {"name": "Garlic Rasam", "eggy": "VEG"}, "CURD BASE": {"name": "Sweet Lassi", "eggy": "VEG"}, "SALAD/SPROUTS": {"name": "Onion\\Chilli\\Lemon", "eggy": "VEG"}, "SWEETS": {"name": "Ice Cream", "eggy": "VEG"}}, "sk": {"SNACKS": {"name": "Corn Cheese Balls", "eggy": "VEG"}, "ACCOMPANIMENTS": {"name": "Tomato Sauce", "eggy": "VEG"}, "TEA/COFFEE/MILK": {"name": "Tea/Coffee/Milk", "eggy": "VEG"}}, "dn": {"INDIAN BREAD": {"name": "Laccha Paratha/ Tawa Paratha", "eggy": "VEG"}, "VEG GRAVY": {"name": "Mt", "eggy": "VEG"}, "VEG DRY/ STARTERS": {"name": "Assorted Vegetable Fry Dry", "eggy": "VEG"}, "FLAVORED RICE": {"name": "Mexican Rice", "eggy": "VEG"}, "PLAIN RICE": {"name": "Plain Rice", "eggy": "VEG"}, "DAL": {"name": "Green Moong Dal", "eggy": "VEG"}, "SAMBAR OR RASAM": {"name": "Tamarind Sambhar", "eggy": "VEG"}, "CURD BASE": {"name": "Curd", "eggy": "VEG"}, "SALAD/SPROUTS": {"name": "Pasta Salad", "eggy": "VEG"}, "SWEETS": {"name": "Block Halwa", "eggy": "VEG"}, "PANEER": {"name": "Paneer Butter Masala", "eggy": "VEG"}, "CHICKEN": {"name": "Chicken Butter Masala", "eggy": "NON"}}, "bfTimings": {"start": "07:45AM", "end": "10:00AM"}, "lnTimings": {"start": "12:45PM", "end": "02:30PM"}, "skTimings": {"start": "04:30PM", "end": "05:45PM"}, "dnTimings": {"start": "07:30PM", "end": "09:30PM"}}, "1": {"bf": {"BREAKFAST 1": {"name": "Poha", "eggy": "VEG"}, "BREAKFAST 2": {"name": "Masala Upma", "eggy": "VEG"}, "SAMBAR OR KETCHUP": {"name": "Mt", "eggy": "VEG"}, "CURD": {"name": "Mt", "eggy": "VEG"}, "CHUTNEY": {"name": "Coconut Chutney", "eggy": "VEG"}, "EGG": {"name": "Omelette", "eggy": "VEG"}, "JUICE/MILK SHAKE": {"name": "Mt", "eggy": "VEG"}}, "ln": {"INDIAN BREAD": {"name": "Dal Chapati", "eggy": "VEG"}, "VEG GRAVY": {"name": "Kadai Vegetable", "eggy": "VEG"}, "VEG DRY/ STARTERS": {"name": "Stuffed Capsicum", "eggy": "VEG"}, "FLAVORED RICE": {"name": "Lemon Rice", "eggy": "VEG"}, "PLAIN RICE": {"name": "Plain Rice", "eggy": "VEG"}, "DAL": {"name": "Dal Tadka", "eggy": "VEG"}, "SAMBAR OR RASAM": {"name": "Pepper Rasam", "eggy": "VEG"}, "CURD BASE": {"name": "Curd", "eggy": "VEG"}, "SALAD/SPROUTS": {"name": "Green Salad", "eggy": "VEG"}, "SWEETS": {"name": "Rice Kheer", "eggy": "VEG"}}, "sk": {"SNACKS": {"name": "Samosa", "eggy": "VEG"}, "ACCOMPANIMENTS": {"name": "Imli Chutney", "eggy": "VEG"}, "TEA/COFFEE/MILK": {"name": "Tea/Coffee/Milk", "eggy": "VEG"}}, "dn": {"INDIAN BREAD": {"name": "Mysore Dosa", "eggy": "VEG"}, "VEG GRAVY": {"name": "Gobi Manchurian (Dry)", "eggy": "VEG"}, "VEG DRY/ STARTERS": {"name": "Aloo Masala", "eggy": "VEG"}, "FLAVORED RICE": {"name": "Fried Rice", "eggy": "VEG"}, "PLAIN RICE": {"name": "Rice", "eggy": "VEG"}, "DAL": {"name": "Yellow Dal Tadka", "eggy": "VEG"}, "SAMBAR OR RASAM": {"name": "Sambhar", "eggy": "VEG"}, "CURD BASE": {"name": "Curd", "eggy": "VEG"}, "SALAD/SPROUTS": {"name": "Sprouts Salad", "eggy": "VEG"}, "SWEETS": {"name": "Cupcake", "eggy": "VEG"}, "PANEER": {"name": "Mt", "eggy": "VEG"}, "CHICKEN": {"name": "Mt", "eggy": "VEG"}}, "bfTimings": {"start": "07:30AM", "end": "09:45AM"}, "lnTimings": {"start": "12:30PM", "end": "02:15PM"}, "skTimings": {"start": "04:30PM", "end": "05:45PM"}, "dnTimings": {"start": "07:30PM", "end": "09:30PM"}}, "2": {"bf": {"BREAKFAST 1": {"name": "Bedmi Puri", "eggy": "VEG"}, "BREAKFAST 2": {"name": "Vermicilli Upma", "eggy": "VEG"}, "SAMBAR OR KETCHUP": {"name": "Mt", "eggy": "VEG"}, "CURD": {"name": "Aloo Subzi", "eggy": "VEG"}, "CHUTNEY": {"name": "Mt", "eggy": "VEG"}, "EGG": {"name": "Mt", "eggy": "VEG"}, "JUICE/MILK SHAKE": {"name": "Mt", "eggy": "VEG"}}, "ln": {"INDIAN BREAD": {"name": "Methi Chapati", "eggy": "VEG"}, "VEG GRAVY": {"name": "Tomato Sev Curry/Dahi Arbi", "eggy": "VEG"}, "VEG DRY/ STARTERS": {"name": "French Fries", "eggy": "VEG"}, "FLAVORED RICE": {"name": "Puliogre", "eggy": "VEG"}, "PLAIN RICE": {"name": "Plain Rice", "eggy": "VEG"}, "DAL": {"name": "Masoor Dal", "eggy": "VEG"}, "SAMBAR OR RASAM": {"name": "Vegetable Sambhar", "eggy": "VEG"}, "CURD BASE": {"name": "Curd", "eggy": "VEG"}, "SALAD/SPROUTS": {"name": "Tomato+Onion+Lemon Only", "eggy": "VEG"}, "SWEETS": {"name": "Vanilla Milkshake", "eggy": "VEG"}}, "sk": {"SNACKS": {"name": "Bread Pakoda", "eggy": "VEG"}, "ACCOMPANIMENTS": {"name": "Ketchup", "eggy": "VEG"}, "TEA/COFFEE/MILK": {"name": "Tea/Coffee/Milk", "eggy": "VEG"}}, "dn": {"INDIAN BREAD": {"name": "Ajwain Chapati", "eggy": "VEG"}, "VEG GRAVY": {"name": "Aloo Gobi Mutter (Home Style)", "eggy": "VEG"}, "VEG DRY/ STARTERS": {"name": "Banana Poriyal", "eggy": "VEG"}, "FLAVORED RICE": {"name": "Veg Pulao", "eggy": "VEG"}, "PLAIN RICE": {"name": "Rice", "eggy": "VEG"}, "DAL": {"name": "Rajma Masala", "eggy": "VEG"}, "SAMBAR OR RASAM": {"name": "Methi Leaves Sambar", "eggy": "VEG"}, "CURD BASE": {"name": "Curd", "eggy": "VEG"}, "SALAD/SPROUTS": {"name": "Pasta Salad", "eggy": "VEG"}, "SWEETS": {"name": "Jalebi+Rabri", "eggy": "VEG"}, "PANEER": {"name": "Mt", "eggy": "VEG"}, "CHICKEN": {"name": "Mt", "eggy": "VEG"}}, "bfTimings": {"start": "07:30AM", "end": "09:45AM"}, "lnTimings": {"start": "12:30PM", "end": "02:15PM"}, "skTimings": {"start": "04:30PM", "end": "05:45PM"}, "dnTimings": {"start": "07:30PM", "end": "09:30PM"}}, "3": {"bf": {"BREAKFAST 1": {"name": "Aloo Gobi Paratha", "eggy": "VEG"}, "BREAKFAST 2": {"name": "Mt", "eggy": "VEG"}, "SAMBAR OR KETCHUP": {"name": "Mt", "eggy": "VEG"}, "CURD": {"name": "Curd", "eggy": "VEG"}, "CHUTNEY": {"name": "Tomato Chutney", "eggy": "VEG"}, "EGG": {"name": "Mt", "eggy": "VEG"}, "JUICE/MILK SHAKE": {"name": "Pineapple Juice", "eggy": "VEG"}}, "ln": {"INDIAN BREAD": {"name": "Pudina Chapati", "eggy": "VEG"}, "VEG GRAVY": {"name": "Home Style Aloo Sabji", "eggy": "VEG"}, "VEG DRY/ STARTERS": {"name": "Aloo Karela Chips", "eggy": "VEG"}, "FLAVORED RICE": {"name": "Donne Biryani", "eggy": "VEG"}, "PLAIN RICE": {"name": "Plain Rice", "eggy": "VEG"}, "DAL": {"name": "Arhar Daal", "eggy": "VEG"}, "SAMBAR OR RASAM": {"name": "Pumpkin Sambar", "eggy": "VEG"}, "CURD BASE": {"name": "Burani Raita", "eggy": "VEG"}, "SALAD/SPROUTS": {"name": "Sprouts Salad", "eggy": "VEG"}, "SWEETS": {"name": "Assorted  Pastry", "eggy": "VEG"}}, "sk": {"SNACKS": {"name": "Dal Pakwaan", "eggy": "VEG"}, "ACCOMPANIMENTS": {"name": "Imli Chutney + Onion", "eggy": "VEG"}, "TEA/COFFEE/MILK": {"name": "Tea/Coffee/Milk", "eggy": "VEG"}}, "dn": {"INDIAN BREAD": {"name": "Tawa Paratha", "eggy": "VEG"}, "VEG GRAVY": {"name": "Mt", "eggy": "VEG"}, "VEG DRY/ STARTERS": {"name": "Honey Chilli Potato", "eggy": "VEG"}, "FLAVORED RICE": {"name": "Jeera Mutter Pulao", "eggy": "VEG"}, "PLAIN RICE": {"name": "Plain Rice", "eggy": "VEG"}, "DAL": {"name": "Yellow Moong Dal", "eggy": "VEG"}, "SAMBAR OR RASAM": {"name": "Drumstick Sambar", "eggy": "VEG"}, "CURD BASE": {"name": "Buttermilk", "eggy": "VEG"}, "SALAD/SPROUTS": {"name": "Green Salad", "eggy": "VEG"}, "SWEETS": {"name": "Milk Peda White Wala", "eggy": "VEG"}, "PANEER": {"name": "Paneer Kurchan", "eggy": "VEG"}, "CHICKEN": {"name": "Chicken Hyderabadi", "eggy": "NON"}}, "bfTimings": {"start": "07:30AM", "end": "09:45AM"}, "lnTimings": {"start": "12:30PM", "end": "02:15PM"}, "skTimings": {"start": "04:30PM", "end": "05:45PM"}, "dnTimings": {"start": "07:30PM", "end": "09:30PM"}}, "4": {"bf": {"BREAKFAST 1": {"name": "Idli", "eggy": "VEG"}, "BREAKFAST 2": {"name": "Vada", "eggy": "VEG"}, "SAMBAR OR KETCHUP": {"name": "Mt", "eggy": "VEG"}, "CURD": {"name": "Chutney", "eggy": "VEG"}, "CHUTNEY": {"name": "Sambhar", "eggy": "VEG"}, "EGG": {"name": "Boilled Egg", "eggy": "EGG"}, "JUICE/MILK SHAKE": {"name": "Mt", "eggy": "VEG"}}, "ln": {"INDIAN BREAD": {"name": "Poori", "eggy": "VEG"}, "VEG GRAVY": {"name": "Aloo Bhajji(Bedmi Puri Style)", "eggy": "VEG"}, "VEG DRY/ STARTERS": {"name": "Kaddu Ki Sabzi", "eggy": "VEG"}, "FLAVORED RICE": {"name": "Bisibilla Bhat", "eggy": "VEG"}, "PLAIN RICE": {"name": "Plain Rice", "eggy": "VEG"}, "DAL": {"name": "Masoor Dal Tadka", "eggy": "VEG"}, "SAMBAR OR RASAM": {"name": "Coriander Jeera Rasam", "eggy": "VEG"}, "CURD BASE": {"name": "Curd", "eggy": "VEG"}, "SALAD/SPROUTS": {"name": "Black Chana Salad W Vegatable", "eggy": "VEG"}, "SWEETS": {"name": "Ice Cream", "eggy": "VEG"}}, "sk": {"SNACKS": {"name": "Pani Puri", "eggy": "VEG"}, "ACCOMPANIMENTS": {"name": "Meetha And Khatta Pani", "eggy": "VEG"}, "TEA/COFFEE/MILK": {"name": "Tea/Coffee/Milk", "eggy": "VEG"}}, "dn": {"INDIAN BREAD": {"name": "Ajwain Chapati", "eggy": "VEG"}, "VEG GRAVY": {"name": "Capsicum Tomato Masala", "eggy": "VEG"}, "VEG DRY/ STARTERS": {"name": "Aloo Fry", "eggy": "VEG"}, "FLAVORED RICE": {"name": "Live Red Pasta", "eggy": "VEG"}, "PLAIN RICE": {"name": "Plain Rice", "eggy": "VEG"}, "DAL": {"name": "Toor Dal Tadka", "eggy": "VEG"}, "SAMBAR OR RASAM": {"name": "Veg Sambar", "eggy": "VEG"}, "CURD BASE": {"name": "Curd", "eggy": "VEG"}, "SALAD/SPROUTS": {"name": "Punjabi Salad", "eggy": "VEG"}, "SWEETS": {"name": "Strawberry Milkshake", "eggy": "VEG"}, "PANEER": {"name": "Mt", "eggy": "VEG"}, "CHICKEN": {"name": "Mt", "eggy": "VEG"}}, "bfTimings": {"start": "07:30AM", "end": "09:45AM"}, "lnTimings": {"start": "12:30PM", "end": "02:15PM"}, "skTimings": {"start": "04:30PM", "end": "05:45PM"}, "dnTimings": {"start": "07:30PM", "end": "09:30PM"}}, "5": {"bf": {"BREAKFAST 1": {"name": "Onion Tomato Uttapam", "eggy": "VEG"}, "BREAKFAST 2": {"name": "Cut Fruit", "eggy": "VEG"}, "SAMBAR OR KETCHUP": {"name": "Mt", "eggy": "VEG"}, "CURD": {"name": "Sambhar", "eggy": "VEG"}, "CHUTNEY": {"name": "Green Chutney", "eggy": "VEG"}, "EGG": {"name": "Egg Bhurji", "eggy": "EGG"}, "JUICE/MILK SHAKE": {"name": "Mt", "eggy": "VEG"}}, "ln": {"INDIAN BREAD": {"name": "Ajwain Chapati", "eggy": "VEG"}, "VEG GRAVY": {"name": "Punjabi Kadhi", "eggy": "VEG"}, "VEG DRY/ STARTERS": {"name": "Kurkuri Bhindi", "eggy": "VEG"}, "FLAVORED RICE": {"name": "Curd Rice", "eggy": "VEG"}, "PLAIN RICE": {"name": "Plain Rice", "eggy": "VEG"}, "DAL": {"name": "Toor Dal", "eggy": "VEG"}, "SAMBAR OR RASAM": {"name": "Rasam", "eggy": "VEG"}, "CURD BASE": {"name": "Lemonade", "eggy": "VEG"}, "SALAD/SPROUTS": {"name": "Corn Cucumber  Salad", "eggy": "VEG"}, "SWEETS": {"name": "Kalakand", "eggy": "VEG"}}, "sk": {"SNACKS": {"name": "Vada Pav W Mirchi", "eggy": "VEG"}, "ACCOMPANIMENTS": {"name": "Mt", "eggy": "VEG"}, "TEA/COFFEE/MILK": {"name": "Tea/Coffee/Milk", "eggy": "VEG"}}, "dn": {"INDIAN BREAD": {"name": "Tawa Paratha", "eggy": "VEG"}, "VEG GRAVY": {"name": "Mt", "eggy": "VEG"}, "VEG DRY/ STARTERS": {"name": "Dondakaya Sabji", "eggy": "VEG"}, "FLAVORED RICE": {"name": "Mt", "eggy": "VEG"}, "PLAIN RICE": {"name": "Plain Rice", "eggy": "VEG"}, "DAL": {"name": "Lobia Masala", "eggy": "VEG"}, "SAMBAR OR RASAM": {"name": "Vendakkai Sambar", "eggy": "VEG"}, "CURD BASE": {"name": "Curd", "eggy": "VEG"}, "SALAD/SPROUTS": {"name": "Green Salad", "eggy": "VEG"}, "SWEETS": {"name": "Gulab Jamun", "eggy": "VEG"}, "PANEER": {"name": "Veg Biryani / Mutter Paneer", "eggy": "VEG"}, "CHICKEN": {"name": "Chicken Biryani", "eggy": "NON"}}, "bfTimings": {"start": "07:30AM", "end": "09:45AM"}, "lnTimings": {"start": "12:30PM", "end": "02:15PM"}, "skTimings": {"start": "04:30PM", "end": "05:45PM"}, "dnTimings": {"start": "07:30PM", "end": "09:30PM"}}, "6": {"bf": {"BREAKFAST 1": {"name": "Podi Masala Dosa", "eggy": "VEG"}, "BREAKFAST 2": {"name": "Banana", "eggy": "VEG"}, "SAMBAR OR KETCHUP": {"name": "Veg Sambhar", "eggy": "VEG"}, "CURD": {"name": "Mt", "eggy": "VEG"}, "CHUTNEY": {"name": "Coconut Chutney", "eggy": "VEG"}, "EGG": {"name": "Mt", "eggy": "VEG"}, "JUICE/MILK SHAKE": {"name": "Mt", "eggy": "VEG"}}, "ln": {"INDIAN BREAD": {"name": "Chapati", "eggy": "VEG"}, "VEG GRAVY": {"name": "Egg Curry/Malai Kofta", "eggy": "EGG"}, "VEG DRY/ STARTERS": {"name": "Stir Fried Corn And Vegetables", "eggy": "VEG"}, "FLAVORED RICE": {"name": "Veg Pulao", "eggy": "VEG"}, "PLAIN RICE": {"name": "Plain Rice", "eggy": "VEG"}, "DAL": {"name": "Toor Daal", "eggy": "VEG"}, "SAMBAR OR RASAM": {"name": "Carrot Sambhar", "eggy": "VEG"}, "CURD BASE": {"name": "Curd", "eggy": "VEG"}, "SALAD/SPROUTS": {"name": "Green Salad", "eggy": "VEG"}, "SWEETS": {"name": "Boondi Laddoo", "eggy": "VEG"}}, "sk": {"SNACKS": {"name": "Kachori", "eggy": "VEG"}, "ACCOMPANIMENTS": {"name": "Imly Chutney", "eggy": "VEG"}, "TEA/COFFEE/MILK": {"name": "Tea/Coffee/Milk", "eggy": "VEG"}}, "dn": {"INDIAN BREAD": {"name": "Ajwain Chapati", "eggy": "VEG"}, "VEG GRAVY": {"name": "Black Chana Masala", "eggy": "VEG"}, "VEG DRY/ STARTERS": {"name": "French Fries", "eggy": "VEG"}, "FLAVORED RICE": {"name": "Garlic Fried Rice", "eggy": "VEG"}, "PLAIN RICE": {"name": "Rice", "eggy": "VEG"}, "DAL": {"name": "Rajma Masala", "eggy": "VEG"}, "SAMBAR OR RASAM": {"name": "Onion Sambar", "eggy": "VEG"}, "CURD BASE": {"name": "Butter Milk", "eggy": "VEG"}, "SALAD/SPROUTS": {"name": "Tomato+Onion+Lemon Only", "eggy": "VEG"}, "SWEETS": {"name": "Moong Dal Halwa", "eggy": "VEG"}, "PANEER": {"name": "Mt", "eggy": "VEG"}, "CHICKEN": {"name": "Mt", "eggy": "VEG"}}, "bfTimings": {"start": "07:45AM", "end": "10:00AM"}, "lnTimings": {"start": "12:45PM", "end": "02:30PM"}, "skTimings": {"start": "04:30PM", "end": "05:45PM"}, "dnTimings": {"start": "07:30PM", "end": "09:30PM"}}}, "dates": {"17-03-2024": "0", "24-03-2024": "0", "11-03-2024": "1", "18-03-2024": "1", "12-03-2024": "2", "19-03-2024": "2", "13-03-2024": "3", "20-03-2024": "3", "14-03-2024": "4", "21-03-2024": "4", "15-03-2024": "5", "22-03-2024": "5", "16-03-2024": "6", "23-03-2024": "6"}, "items": {"bf": ["BREAKFAST 1", "BREAKFAST 2", "SAMBAR OR KETCHUP", "CURD", "CHUTNEY", "EGG", "JUICE/MILK SHAKE"], "ln": ["INDIAN BREAD", "VEG GRAVY", "VEG DRY/ STARTERS", "FLAVORED RICE", "PLAIN RICE", "DAL", "SAMBAR OR RASAM", "CURD BASE", "SALAD/SPROUTS", "SWEETS"], "sk": ["SNACKS", "ACCOMPANIMENTS", "TEA/COFFEE/MILK"], "dn": ["INDIAN BREAD", "VEG GRAVY", "VEG DRY/ STARTERS", "FLAVORED RICE", "PLAIN RICE", "DAL", "SAMBAR OR RASAM", "CURD BASE", "SALAD/SPROUTS", "SWEETS", "PANEER", "CHICKEN"]}}