{"menu": {"0": {"bf": {"BREAKFAST 1": {"name": "Aloo Paratha", "eggy": "VEG"}, "BREAKFAST 2": {"name": "Curd", "eggy": "VEG"}, "SAMBAR OR KETCHUP": {"name": "Tomato Garlic Chutney", "eggy": "VEG"}, "CURD": {"name": "Mt", "eggy": "VEG"}, "CHUTNEY": {"name": "Mt", "eggy": "VEG"}, "EGG": {"name": "Mt", "eggy": "VEG"}, "JUICE/MILK SHAKE": {"name": "Watermelon Juice", "eggy": "VEG"}}, "ln": {"INDIAN BREAD": {"name": "Bhature", "eggy": "VEG"}, "VEG GRAVY": {"name": "Pindi Chole", "eggy": "VEG"}, "VEG DRY/ STARTERS": {"name": "Aloo Gobhi", "eggy": "VEG"}, "FLAVORED RICE": {"name": "Veg Pulao", "eggy": "VEG"}, "PLAIN RICE": {"name": "Plain Rice", "eggy": "VEG"}, "DAL": {"name": "Dal Fry", "eggy": "VEG"}, "SAMBAR OR RASAM": {"name": "Garlic Rasam", "eggy": "VEG"}, "CURD BASE": {"name": "Sweet Lassi", "eggy": "VEG"}, "SALAD/SPROUTS": {"name": "Onion\\Chilli\\Lemon", "eggy": "VEG"}, "SWEETS": {"name": "Ice Cream", "eggy": "VEG"}}, "sk": {"SNACKS": {"name": "Kachori", "eggy": "VEG"}, "ACCOMPANIMENTS": {"name": "Chutney", "eggy": "VEG"}, "TEA/COFFEE/MILK": {"name": "Tea/Coffee/Milk", "eggy": "VEG"}}, "dn": {"INDIAN BREAD": {"name": "Tawa Paratha", "eggy": "VEG"}, "VEG GRAVY": {"name": "Mt", "eggy": "VEG"}, "VEG DRY/ STARTERS": {"name": "Aloo Pyaaz", "eggy": "VEG"}, "FLAVORED RICE": {"name": "Veg Pulao", "eggy": "VEG"}, "PLAIN RICE": {"name": "Rice", "eggy": "VEG"}, "DAL": {"name": "Green Moong Dal", "eggy": "VEG"}, "SAMBAR OR RASAM": {"name": "Tarmarind Rasam", "eggy": "VEG"}, "CURD BASE": {"name": "Curd", "eggy": "VEG"}, "SALAD/SPROUTS": {"name": "Green Salad", "eggy": "VEG"}, "SWEETS": {"name": "Gulab Jamun", "eggy": "VEG"}, "PANEER": {"name": "Paneer Kurchan", "eggy": "VEG"}, "CHICKEN": {"name": "Chicken Kurchan", "eggy": "NON"}}, "bfTimings": {"start": "07:45AM", "end": "10:00AM"}, "lnTimings": {"start": "12:45PM", "end": "02:30PM"}, "skTimings": {"start": "04:30PM", "end": "05:45PM"}, "dnTimings": {"start": "07:30PM", "end": "09:30PM"}}, "1": {"bf": {"BREAKFAST 1": {"name": "Idli", "eggy": "VEG"}, "BREAKFAST 2": {"name": "Uddin Vada", "eggy": "VEG"}, "SAMBAR OR KETCHUP": {"name": "Veg Sambar", "eggy": "VEG"}, "CURD": {"name": "Mt", "eggy": "VEG"}, "CHUTNEY": {"name": "Coconut Chutney", "eggy": "VEG"}, "EGG": {"name": "Boiled Egg", "eggy": "EGG"}, "JUICE/MILK SHAKE": {"name": "Mt", "eggy": "VEG"}}, "ln": {"INDIAN BREAD": {"name": "Dal Chapati", "eggy": "VEG"}, "VEG GRAVY": {"name": "Gutti Vankaya Curry", "eggy": "VEG"}, "VEG DRY/ STARTERS": {"name": "Subz Maloni", "eggy": "VEG"}, "FLAVORED RICE": {"name": "Curd Rice", "eggy": "VEG"}, "PLAIN RICE": {"name": "Plain Rice", "eggy": "VEG"}, "DAL": {"name": "Dal Tadka", "eggy": "VEG"}, "SAMBAR OR RASAM": {"name": "Pepper Rasam", "eggy": "VEG"}, "CURD BASE": {"name": "Lemonade", "eggy": "VEG"}, "SALAD/SPROUTS": {"name": "Green Salad", "eggy": "VEG"}, "SWEETS": {"name": "Rasgulla", "eggy": "VEG"}}, "sk": {"SNACKS": {"name": "Veg Puff", "eggy": "VEG"}, "ACCOMPANIMENTS": {"name": "Mt", "eggy": "VEG"}, "TEA/COFFEE/MILK": {"name": "Tea/Coffee/Milk", "eggy": "VEG"}}, "dn": {"INDIAN BREAD": {"name": "Ajwain Chapati", "eggy": "VEG"}, "VEG GRAVY": {"name": "Malai Kofta", "eggy": "VEG"}, "VEG DRY/ STARTERS": {"name": "Kadai Veg", "eggy": "VEG"}, "FLAVORED RICE": {"name": "Achari Dum Biryani", "eggy": "VEG"}, "PLAIN RICE": {"name": "Rice", "eggy": "VEG"}, "DAL": {"name": "Masoor Dal", "eggy": "VEG"}, "SAMBAR OR RASAM": {"name": "Pepper Rasam", "eggy": "VEG"}, "CURD BASE": {"name": "Boondi Raita", "eggy": "VEG"}, "SALAD/SPROUTS": {"name": "Russian Salad", "eggy": "VEG"}, "SWEETS": {"name": "Badam Milk", "eggy": "VEG"}, "PANEER": {"name": "Mt", "eggy": "VEG"}, "CHICKEN": {"name": "Mt", "eggy": "VEG"}}, "bfTimings": {"start": "07:30AM", "end": "09:45AM"}, "lnTimings": {"start": "12:30PM", "end": "02:15PM"}, "skTimings": {"start": "04:30PM", "end": "05:45PM"}, "dnTimings": {"start": "07:30PM", "end": "09:30PM"}}, "2": {"bf": {"BREAKFAST 1": {"name": "Pessarattu", "eggy": "VEG"}, "BREAKFAST 2": {"name": "Kara Bhat", "eggy": "VEG"}, "SAMBAR OR KETCHUP": {"name": "Mt", "eggy": "VEG"}, "CURD": {"name": "Sambar", "eggy": "VEG"}, "CHUTNEY": {"name": "Coconut Chutney", "eggy": "VEG"}, "EGG": {"name": "Mt", "eggy": "VEG"}, "JUICE/MILK SHAKE": {"name": "Pineapple Juice", "eggy": "VEG"}}, "ln": {"INDIAN BREAD": {"name": "Methi Chapati", "eggy": "VEG"}, "VEG GRAVY": {"name": "Subz Achari", "eggy": "VEG"}, "VEG DRY/ STARTERS": {"name": "Veg Poriyal", "eggy": "VEG"}, "FLAVORED RICE": {"name": "Jeera Rice", "eggy": "VEG"}, "PLAIN RICE": {"name": "Plain Rice", "eggy": "VEG"}, "DAL": {"name": "Dal Tadka", "eggy": "VEG"}, "SAMBAR OR RASAM": {"name": "Vegetable Sambhar", "eggy": "VEG"}, "CURD BASE": {"name": "Butter Milk", "eggy": "VEG"}, "SALAD/SPROUTS": {"name": "Green Salad", "eggy": "VEG"}, "SWEETS": {"name": "Suji Halwa", "eggy": "VEG"}}, "sk": {"SNACKS": {"name": "Aloo Samosa", "eggy": "VEG"}, "ACCOMPANIMENTS": {"name": "Chutney", "eggy": "VEG"}, "TEA/COFFEE/MILK": {"name": "Tea/Coffee/Milk", "eggy": "VEG"}}, "dn": {"INDIAN BREAD": {"name": "Chapati", "eggy": "VEG"}, "VEG GRAVY": {"name": "Punjabi Dum Aloo", "eggy": "VEG"}, "VEG DRY/ STARTERS": {"name": "Arbi Pepper Fry", "eggy": "VEG"}, "FLAVORED RICE": {"name": "Mexican Rice", "eggy": "VEG"}, "PLAIN RICE": {"name": "Rice", "eggy": "VEG"}, "DAL": {"name": "Dal Makhani", "eggy": "VEG"}, "SAMBAR OR RASAM": {"name": "Methi Leaves Sambar", "eggy": "VEG"}, "CURD BASE": {"name": "Curd", "eggy": "VEG"}, "SALAD/SPROUTS": {"name": "Chickpeas Salad", "eggy": "VEG"}, "SWEETS": {"name": "Rice Payasam", "eggy": "VEG"}, "PANEER": {"name": "Mt", "eggy": "VEG"}, "CHICKEN": {"name": "Mt", "eggy": "VEG"}}, "bfTimings": {"start": "07:30AM", "end": "09:45AM"}, "lnTimings": {"start": "12:30PM", "end": "02:15PM"}, "skTimings": {"start": "04:30PM", "end": "05:45PM"}, "dnTimings": {"start": "07:30PM", "end": "09:30PM"}}, "3": {"bf": {"BREAKFAST 1": {"name": "Vermiceli Upma", "eggy": "VEG"}, "BREAKFAST 2": {"name": "Cut Fruits", "eggy": "VEG"}, "SAMBAR OR KETCHUP": {"name": "Mt", "eggy": "VEG"}, "CURD": {"name": "Mt", "eggy": "VEG"}, "CHUTNEY": {"name": "Corinder Chutney", "eggy": "VEG"}, "EGG": {"name": "Omlette", "eggy": "EGG"}, "JUICE/MILK SHAKE": {"name": "Mt", "eggy": "VEG"}}, "ln": {"INDIAN BREAD": {"name": "Palak Puri", "eggy": "VEG"}, "VEG GRAVY": {"name": "Aloo Bhajji", "eggy": "VEG"}, "VEG DRY/ STARTERS": {"name": "Beetroot Porial", "eggy": "VEG"}, "FLAVORED RICE": {"name": "Corn Pulao", "eggy": "VEG"}, "PLAIN RICE": {"name": "Plain Rice", "eggy": "VEG"}, "DAL": {"name": "Yellow Dal Tadka", "eggy": "VEG"}, "SAMBAR OR RASAM": {"name": "Coriander Jeera Rasam", "eggy": "VEG"}, "CURD BASE": {"name": "Curd", "eggy": "VEG"}, "SALAD/SPROUTS": {"name": "Punjabi Salad", "eggy": "VEG"}, "SWEETS": {"name": "Ice Cream", "eggy": "VEG"}}, "sk": {"SNACKS": {"name": "Pav Bhaji", "eggy": "VEG"}, "ACCOMPANIMENTS": {"name": "Onion", "eggy": "VEG"}, "TEA/COFFEE/MILK": {"name": "Tea/Coffee/Milk", "eggy": "VEG"}}, "dn": {"INDIAN BREAD": {"name": "Tawa Paratha", "eggy": "VEG"}, "VEG GRAVY": {"name": "Mt", "eggy": "VEG"}, "VEG DRY/ STARTERS": {"name": "Honey Chilly Potato", "eggy": "VEG"}, "FLAVORED RICE": {"name": "Jeera Mutter Pulao", "eggy": "VEG"}, "PLAIN RICE": {"name": "Rice", "eggy": "VEG"}, "DAL": {"name": "Dal Fry", "eggy": "VEG"}, "SAMBAR OR RASAM": {"name": "Drumstick Sambar", "eggy": "VEG"}, "CURD BASE": {"name": "Curd", "eggy": "VEG"}, "SALAD/SPROUTS": {"name": "Green Salad", "eggy": "VEG"}, "SWEETS": {"name": "Marble Cake", "eggy": "VEG"}, "PANEER": {"name": "Paneer Tikka Masala", "eggy": "VEG"}, "CHICKEN": {"name": "Chicken Butter Masala", "eggy": "NON"}}, "bfTimings": {"start": "07:30AM", "end": "09:45AM"}, "lnTimings": {"start": "12:30PM", "end": "02:15PM"}, "skTimings": {"start": "04:30PM", "end": "05:45PM"}, "dnTimings": {"start": "07:30PM", "end": "09:30PM"}}, "4": {"bf": {"BREAKFAST 1": {"name": "Masala Uttapam", "eggy": "VEG"}, "BREAKFAST 2": {"name": "Sabudana Upma", "eggy": "VEG"}, "SAMBAR OR KETCHUP": {"name": "Veg Sambar", "eggy": "VEG"}, "CURD": {"name": "Mt", "eggy": "VEG"}, "CHUTNEY": {"name": "Coconut Chutney", "eggy": "VEG"}, "EGG": {"name": "Mt", "eggy": "VEG"}, "JUICE/MILK SHAKE": {"name": "Mt", "eggy": "VEG"}}, "ln": {"INDIAN BREAD": {"name": "Ajwain Chapati", "eggy": "VEG"}, "VEG GRAVY": {"name": "Subz Hyderabadi", "eggy": "VEG"}, "VEG DRY/ STARTERS": {"name": "Lauki Chana", "eggy": "VEG"}, "FLAVORED RICE": {"name": "Vangi Bhatt", "eggy": "VEG"}, "PLAIN RICE": {"name": "Plain Rice", "eggy": "VEG"}, "DAL": {"name": "Dal Tadka", "eggy": "VEG"}, "SAMBAR OR RASAM": {"name": "Carrot Sambhar", "eggy": "VEG"}, "CURD BASE": {"name": "Curd", "eggy": "VEG"}, "SALAD/SPROUTS": {"name": "Sprouts Salad", "eggy": "VEG"}, "SWEETS": {"name": "Rasgula", "eggy": "VEG"}}, "sk": {"SNACKS": {"name": "Paani Puri", "eggy": "VEG"}, "ACCOMPANIMENTS": {"name": "Mt", "eggy": "VEG"}, "TEA/COFFEE/MILK": {"name": "Tea/Coffee/Milk", "eggy": "VEG"}}, "dn": {"INDIAN BREAD": {"name": "Methi Chapati", "eggy": "VEG"}, "VEG GRAVY": {"name": "Veg Khurchan", "eggy": "VEG"}, "VEG DRY/ STARTERS": {"name": "Stir Fry Veg With Salt And Pepper", "eggy": "VEG"}, "FLAVORED RICE": {"name": "Veg Shezwaan Noodles", "eggy": "VEG"}, "PLAIN RICE": {"name": "Rice", "eggy": "VEG"}, "DAL": {"name": "Rajma Masala", "eggy": "VEG"}, "SAMBAR OR RASAM": {"name": "Pumpkin Rasam", "eggy": "VEG"}, "CURD BASE": {"name": "Curd", "eggy": "VEG"}, "SALAD/SPROUTS": {"name": "Tossed Salad", "eggy": "VEG"}, "SWEETS": {"name": "Besan Laddu", "eggy": "VEG"}, "PANEER": {"name": "Mt", "eggy": "VEG"}, "CHICKEN": {"name": "Mt", "eggy": "VEG"}}, "bfTimings": {"start": "07:30AM", "end": "09:45AM"}, "lnTimings": {"start": "12:30PM", "end": "02:15PM"}, "skTimings": {"start": "04:30PM", "end": "05:45PM"}, "dnTimings": {"start": "07:30PM", "end": "09:30PM"}}, "5": {"bf": {"BREAKFAST 1": {"name": "Gobhi Paratha", "eggy": "VEG"}, "BREAKFAST 2": {"name": "Pongal", "eggy": "VEG"}, "SAMBAR OR KETCHUP": {"name": "Mt", "eggy": "VEG"}, "CURD": {"name": "Curd", "eggy": "VEG"}, "CHUTNEY": {"name": "Peanut Garlic Chutney", "eggy": "VEG"}, "EGG": {"name": "Boiled Egg", "eggy": "EGG"}, "JUICE/MILK SHAKE": {"name": "Mt", "eggy": "VEG"}}, "ln": {"INDIAN BREAD": {"name": "Palak Chapati", "eggy": "VEG"}, "VEG GRAVY": {"name": "Kadhi Pokada", "eggy": "VEG"}, "VEG DRY/ STARTERS": {"name": "Sorekai Batani Paliya", "eggy": "VEG"}, "FLAVORED RICE": {"name": "Veg Pulao", "eggy": "VEG"}, "PLAIN RICE": {"name": "Plain Rice", "eggy": "VEG"}, "DAL": {"name": "Dal Makhani", "eggy": "VEG"}, "SAMBAR OR RASAM": {"name": "Veg Sambar", "eggy": "VEG"}, "CURD BASE": {"name": "Masala Chass", "eggy": "VEG"}, "SALAD/SPROUTS": {"name": "Green Salad", "eggy": "VEG"}, "SWEETS": {"name": "Gulab Jamun", "eggy": "VEG"}}, "sk": {"SNACKS": {"name": "Masala Idly", "eggy": "VEG"}, "ACCOMPANIMENTS": {"name": "Coconut Chutney", "eggy": "VEG"}, "TEA/COFFEE/MILK": {"name": "Tea/Coffee/Milk", "eggy": "VEG"}}, "dn": {"INDIAN BREAD": {"name": "Tawa Paratha", "eggy": "VEG"}, "VEG GRAVY": {"name": "Veg Kohlapuri", "eggy": "VEG"}, "VEG DRY/ STARTERS": {"name": "Aloo Karela Chips", "eggy": "VEG"}, "FLAVORED RICE": {"name": "Pasta (Live)", "eggy": "VEG"}, "PLAIN RICE": {"name": "Rice", "eggy": "VEG"}, "DAL": {"name": "Dal Panchmal", "eggy": "VEG"}, "SAMBAR OR RASAM": {"name": "Vendakkai Sambar", "eggy": "VEG"}, "CURD BASE": {"name": "Boondi Raita", "eggy": "VEG"}, "SALAD/SPROUTS": {"name": "Green Salad", "eggy": "VEG"}, "SWEETS": {"name": "Chocolate Pastry", "eggy": "VEG"}, "PANEER": {"name": "Kadhai Paneer W Veg Biryani Only For Veg", "eggy": "VEG"}, "CHICKEN": {"name": "Chicken Biryani", "eggy": "NON"}}, "bfTimings": {"start": "07:30AM", "end": "09:45AM"}, "lnTimings": {"start": "12:30PM", "end": "02:15PM"}, "skTimings": {"start": "04:30PM", "end": "05:45PM"}, "dnTimings": {"start": "07:30PM", "end": "09:30PM"}}, "6": {"bf": {"BREAKFAST 1": {"name": "Poha", "eggy": "VEG"}, "BREAKFAST 2": {"name": "Podi Masala Dosa", "eggy": "VEG"}, "SAMBAR OR KETCHUP": {"name": "Veg Sambar", "eggy": "VEG"}, "CURD": {"name": "Mt", "eggy": "VEG"}, "CHUTNEY": {"name": "Coconut Chutney", "eggy": "VEG"}, "EGG": {"name": "Mt", "eggy": "VEG"}, "JUICE/MILK SHAKE": {"name": "Mt", "eggy": "VEG"}}, "ln": {"INDIAN BREAD": {"name": "Methi Chapati", "eggy": "VEG"}, "VEG GRAVY": {"name": "Aloo Mutter Masala", "eggy": "VEG"}, "VEG DRY/ STARTERS": {"name": "Egg Curry/Soyabean Curry", "eggy": "EGG"}, "FLAVORED RICE": {"name": "Curd Rice", "eggy": "VEG"}, "PLAIN RICE": {"name": "Plain Rice", "eggy": "VEG"}, "DAL": {"name": "Toor Daal", "eggy": "VEG"}, "SAMBAR OR RASAM": {"name": "Rasam", "eggy": "VEG"}, "CURD BASE": {"name": "Lemonade", "eggy": "VEG"}, "SALAD/SPROUTS": {"name": "Veg Corn Salad", "eggy": "VEG"}, "SWEETS": {"name": "Mysore Pak", "eggy": "VEG"}}, "sk": {"SNACKS": {"name": "Vada Pao", "eggy": "VEG"}, "ACCOMPANIMENTS": {"name": "Mt", "eggy": "VEG"}, "TEA/COFFEE/MILK": {"name": "Tea/Coffee/Milk", "eggy": "VEG"}}, "dn": {"INDIAN BREAD": {"name": "Ajwain Chapati", "eggy": "VEG"}, "VEG GRAVY": {"name": "Subz Meloni", "eggy": "VEG"}, "VEG DRY/ STARTERS": {"name": "Veg Gravy Manchurian", "eggy": "VEG"}, "FLAVORED RICE": {"name": "Veg Fried Rice", "eggy": "VEG"}, "PLAIN RICE": {"name": "Rice", "eggy": "VEG"}, "DAL": {"name": "Yellow Dal Tadka", "eggy": "VEG"}, "SAMBAR OR RASAM": {"name": "Veg Rasam", "eggy": "VEG"}, "CURD BASE": {"name": "Mix Veg Raita", "eggy": "VEG"}, "SALAD/SPROUTS": {"name": "Pasta Salad", "eggy": "VEG"}, "SWEETS": {"name": "Shrikhand", "eggy": "VEG"}, "PANEER": {"name": "Mt", "eggy": "VEG"}, "CHICKEN": {"name": "Mt", "eggy": "VEG"}}, "bfTimings": {"start": "07:45AM", "end": "10:00AM"}, "lnTimings": {"start": "12:45PM", "end": "02:30PM"}, "skTimings": {"start": "04:30PM", "end": "05:45PM"}, "dnTimings": {"start": "07:30PM", "end": "09:30PM"}}}, "dates": {"01-10-2023": "0", "08-10-2023": "0", "25-09-2023": "1", "02-10-2023": "1", "26-09-2023": "2", "03-10-2023": "2", "27-09-2023": "3", "04-10-2023": "3", "28-09-2023": "4", "05-10-2023": "4", "29-09-2023": "5", "06-10-2023": "5", "30-09-2023": "6", "07-10-2023": "6"}, "items": {"bf": ["BREAKFAST 1", "BREAKFAST 2", "SAMBAR OR KETCHUP", "CURD", "CHUTNEY", "EGG", "JUICE/MILK SHAKE"], "ln": ["INDIAN BREAD", "VEG GRAVY", "VEG DRY/ STARTERS", "FLAVORED RICE", "PLAIN RICE", "DAL", "SAMBAR OR RASAM", "CURD BASE", "SALAD/SPROUTS", "SWEETS"], "sk": ["SNACKS", "ACCOMPANIMENTS", "TEA/COFFEE/MILK"], "dn": ["INDIAN BREAD", "VEG GRAVY", "VEG DRY/ STARTERS", "FLAVORED RICE", "PLAIN RICE", "DAL", "SAMBAR OR RASAM", "CURD BASE", "SALAD/SPROUTS", "SWEETS", "PANEER", "CHICKEN"]}}